LICENSE
README.rst
setup.py
./graphem/QUIC.cpp
cfr_graphem.egg-info/PKG-INFO
cfr_graphem.egg-info/SOURCES.txt
cfr_graphem.egg-info/dependency_links.txt
cfr_graphem.egg-info/not-zip-safe
cfr_graphem.egg-info/requires.txt
cfr_graphem.egg-info/top_level.txt
graphem/GraphEstimation.py
graphem/QUIC.py
graphem/__init__.py
graphem/graph.py
graphem/iridge.py
graphem/solver.py