Metadata-Version: 2.1
Name: cfr-graphem
Version: 0.2.1
Summary: The GraphEM component for CFR
Home-page: https://github.com/fzhu2e/cfr-graphem
Author: Feng Zhu, Julien Emile-Geay
Author-email: fengzhu@usc.edu, julieneg@usc.edu
License: BSD 3-Clause
Keywords: climate field reconstruction
Classifier: Natural Language :: English
Classifier: Programming Language :: Python :: 3.9
Classifier: Programming Language :: Python :: 3.10
License-File: LICENSE
